purei9_unofficial/__init__.py
purei9_unofficial/__main__.py
purei9_unofficial/cloud.py
purei9_unofficial/cloudv2.py
purei9_unofficial/cloudv3.py
purei9_unofficial/cloudv3_gigya.py
purei9_unofficial/common.py
purei9_unofficial/credentialstore.py
purei9_unofficial/imageascii.py
purei9_unofficial/local.py
purei9_unofficial/message.py
purei9_unofficial/util.py
purei9_unofficial/tests/__init__.py
purei9_unofficial/tests/fakerobot.py
purei9_unofficial/tests/test_cloud_v1.py
purei9_unofficial/tests/test_cloud_v2.py
purei9_unofficial/tests/test_cloud_v3.py
purei9_unofficial/tests/test_local.py
purei9_unofficial/tests/util.py
purei9_unofficial-0.0.16.dist-info/LICENSE
purei9_unofficial-0.0.16.dist-info/METADATA
purei9_unofficial-0.0.16.dist-info/WHEEL
purei9_unofficial-0.0.16.dist-info/top_level.txt
purei9_unofficial-0.0.16.dist-info/RECORD
