Metadata-Version: 2.1
Name: purei9_unofficial
Version: 0.0.16
Summary: Small proof-of-concept client to connect to Electrolux and AEG cleaner robots
Home-page: https://github.com/Phype/purei9_unofficial
Author: Philipp Jeitner
Author-email: p.jeitner@posteo.de
Project-URL: Bug Tracker, https://github.com/Phype/purei9_unofficial/issues
Classifier: Programming Language :: Python :: 3
Classifier: License :: OSI Approved :: MIT License
Classifier: Operating System :: OS Independent
Requires-Python: >=3.5
License-File: LICENSE
Requires-Dist: requests
